README.md
setup.py
LastDB/__init__.py
LastDB.egg-info/PKG-INFO
LastDB.egg-info/SOURCES.txt
LastDB.egg-info/dependency_links.txt
LastDB.egg-info/top_level.txt