Metadata-Version: 1.0
Name: LastDB
Version: 0.1.2
Summary: Database using json
Home-page: UNKNOWN
Author: MikaelStave
Author-email: mikael.stave@gmail.com
License: MIT
Platform: UNKNOWN
